awscrt-stubs/__init__.pyi
awscrt-stubs/_test.pyi
awscrt-stubs/auth.pyi
awscrt-stubs/cbor.pyi
awscrt-stubs/checksums.pyi
awscrt-stubs/common.pyi
awscrt-stubs/crypto.pyi
awscrt-stubs/exceptions.pyi
awscrt-stubs/http.pyi
awscrt-stubs/io.pyi
awscrt-stubs/mqtt.pyi
awscrt-stubs/mqtt5.pyi
awscrt-stubs/mqtt_request_response.pyi
awscrt-stubs/py.typed
awscrt-stubs/s3.pyi
awscrt-stubs/websocket.pyi
awscrt-stubs/aio/__init__.pyi
awscrt-stubs/aio/http.pyi
awscrt-stubs/eventstream/__init__.pyi
awscrt-stubs/eventstream/rpc.pyi
build/lib/awscrt-stubs/__init__.pyi
build/lib/awscrt-stubs/_test.pyi
build/lib/awscrt-stubs/auth.pyi
build/lib/awscrt-stubs/cbor.pyi
build/lib/awscrt-stubs/checksums.pyi
build/lib/awscrt-stubs/common.pyi
build/lib/awscrt-stubs/crypto.pyi
build/lib/awscrt-stubs/exceptions.pyi
build/lib/awscrt-stubs/http.pyi
build/lib/awscrt-stubs/io.pyi
build/lib/awscrt-stubs/mqtt.pyi
build/lib/awscrt-stubs/mqtt5.pyi
build/lib/awscrt-stubs/mqtt_request_response.pyi
build/lib/awscrt-stubs/py.typed
build/lib/awscrt-stubs/s3.pyi
build/lib/awscrt-stubs/websocket.pyi
build/lib/awscrt-stubs/aio/__init__.pyi
build/lib/awscrt-stubs/aio/http.pyi
build/lib/awscrt-stubs/eventstream/__init__.pyi
build/lib/awscrt-stubs/eventstream/rpc.pyi
types_awscrt-0.29.2.dist-info/licenses/LICENSE
types_awscrt-0.29.2.dist-info/METADATA
types_awscrt-0.29.2.dist-info/WHEEL
types_awscrt-0.29.2.dist-info/top_level.txt
types_awscrt-0.29.2.dist-info/RECORD
